{
    "fluentMethods": true,
    "relationships": [
        {
            "relationshipName": "course",
            "otherEntityName": "course",
            "relationshipType": "many-to-one",
            "otherEntityField": "id"
        }
    ],
    "fields": [
        {
            "fieldName": "data",
            "fieldType": "LocalDate",
            "fieldValidateRules": [
                "required"
            ]
        },
        {
            "fieldName": "hour",
            "fieldType": "String",
            "fieldValidateRules": [
                "required"
            ]
        },
        {
            "fieldName": "classroom",
            "fieldType": "String",
            "fieldValidateRules": [
                "required"
            ]
        },
        {
            "fieldName": "duration",
            "fieldType": "String"
        },
        {
            "fieldName": "deadline",
            "fieldType": "LocalDate"
        }
    ],
    "changelogDate": "20170511073920",
    "dto": "no",
    "service": "serviceImpl",
    "entityTableName": "exam",
    "pagination": "no"
}
